msserviceprofiler/__init__.py
msserviceprofiler/__main__.py
msserviceprofiler/modelevalstate/__init__.py
msserviceprofiler/modelevalstate/analysis.py
msserviceprofiler/modelevalstate/common.py
msserviceprofiler/modelevalstate/config/__init__.py
msserviceprofiler/modelevalstate/config/base_config.py
msserviceprofiler/modelevalstate/config/config.py
msserviceprofiler/modelevalstate/config/custom_command.py
msserviceprofiler/modelevalstate/config/model_config.py
msserviceprofiler/modelevalstate/config.toml
msserviceprofiler/modelevalstate/data_feature/__init__.py
msserviceprofiler/modelevalstate/data_feature/dataset.py
msserviceprofiler/modelevalstate/data_feature/dataset_with_modin.py
msserviceprofiler/modelevalstate/data_feature/dataset_with_swifter.py
msserviceprofiler/modelevalstate/data_feature/v1.py
msserviceprofiler/modelevalstate/inference/__init__.py
msserviceprofiler/modelevalstate/inference/common.py
msserviceprofiler/modelevalstate/inference/constant.py
msserviceprofiler/modelevalstate/inference/data_format_v1.py
msserviceprofiler/modelevalstate/inference/dataset.py
msserviceprofiler/modelevalstate/inference/file_reader.py
msserviceprofiler/modelevalstate/inference/simulate.py
msserviceprofiler/modelevalstate/inference/simulate_vllm.py
msserviceprofiler/modelevalstate/inference/state_eval_v1.py
msserviceprofiler/modelevalstate/inference/utils.py
msserviceprofiler/modelevalstate/model/__init__.py
msserviceprofiler/modelevalstate/model/xgb_state_model.py
msserviceprofiler/modelevalstate/optimizer/__init__.py
msserviceprofiler/modelevalstate/optimizer/analyze_profiler.py
msserviceprofiler/modelevalstate/optimizer/communication.py
msserviceprofiler/modelevalstate/optimizer/custom_process.py
msserviceprofiler/modelevalstate/optimizer/experience_fine_tunning.py
msserviceprofiler/modelevalstate/optimizer/global_best_custom.py
msserviceprofiler/modelevalstate/optimizer/interfaces/__init__.py
msserviceprofiler/modelevalstate/optimizer/interfaces/benchmark.py
msserviceprofiler-1.2.3.dist-info/METADATA
msserviceprofiler-1.2.3.dist-info/WHEEL
msserviceprofiler-1.2.3.dist-info/entry_points.txt
msserviceprofiler-1.2.3.dist-info/RECORD
