Metadata-Version: 2.4
Name: msserviceprofiler
Version: 1.2.3
Summary: 
Requires-Python: >=3.9,<4.0
Classifier: Programming Language :: Python :: 3
Classifier: Programming Language :: Python :: 3.9
Classifier: Programming Language :: Python :: 3.10
Classifier: Programming Language :: Python :: 3.11
Classifier: Programming Language :: Python :: 3.12
Classifier: Programming Language :: Python :: 3.13
Classifier: Programming Language :: Python :: 3.14
Provides-Extra: real
Provides-Extra: speed
Provides-Extra: train
Requires-Dist: filelock (>=3.13.1,<4.0.0) ; extra == "real" or extra == "train" or extra == "speed"
Requires-Dist: loguru (>=0.7.3,<0.8.0)
Requires-Dist: matplotlib (>=3.7.2,<4.0.0) ; extra == "train" or extra == "speed"
Requires-Dist: modin[all] (>=0.32.0,<0.33.0) ; extra == "speed"
Requires-Dist: pandas
Requires-Dist: psutil (>=6.0.0,<7.0.0)
Requires-Dist: pydantic (>=2.10.5,<3.0.0) ; extra == "real" or extra == "train" or extra == "speed"
Requires-Dist: pydantic-settings (>=2.2.1,<3.0.0) ; extra == "real" or extra == "train" or extra == "speed"
Requires-Dist: pyswarms (>=1.3.0,<2.0.0) ; extra == "real" or extra == "train" or extra == "speed"
Requires-Dist: requests (>=2.32.0,<3.0.0) ; extra == "real" or extra == "train" or extra == "speed"
Requires-Dist: scikit-learn (>=1.3.2,<2.0.0) ; extra == "train" or extra == "speed"
Requires-Dist: scipy (>=1.3.2,<2.0.0)
Requires-Dist: seaborn (>=0.13.2,<0.14.0) ; extra == "train" or extra == "speed"
Requires-Dist: swifter[groupby] (>=1.4.0,<2.0.0) ; extra == "speed"
Requires-Dist: xgboost (==2.0.0) ; extra == "train" or extra == "speed"
